setup.py
Bank/__init__.py
Bank/account.py
Bank/chequing.py
Bank/controller.py
Bank/model.py
Bank/savings.py
Bank/term_savings.py
Bank/transaction_log.py
Bank/view.py
Bank_CLI.egg-info/PKG-INFO
Bank_CLI.egg-info/SOURCES.txt
Bank_CLI.egg-info/dependency_links.txt
Bank_CLI.egg-info/not-zip-safe
Bank_CLI.egg-info/top_level.txt