Metadata-Version: 1.0
Name: Bank-CLI
Version: 1.5
Summary: A command line intepretation of a bank
Home-page: UNKNOWN
Author: Nifesimi Ademoye
Author-email: nifesimifrank@gmail.com
License: UNKNOWN
Platform: UNKNOWN
